jihangsdk/__init__.py
jihangsdk/help.py
jihangsdk-0.3.0.dist-info/DESCRIPTION.rst
jihangsdk-0.3.0.dist-info/METADATA
jihangsdk-0.3.0.dist-info/RECORD
jihangsdk-0.3.0.dist-info/WHEEL
jihangsdk-0.3.0.dist-info/entry_points.txt
jihangsdk-0.3.0.dist-info/metadata.json
jihangsdk-0.3.0.dist-info/top_level.txt
